setup.py
joke861110/__init__.py
joke861110/text.py
joke861110.egg-info/PKG-INFO
joke861110.egg-info/SOURCES.txt
joke861110.egg-info/dependency_links.txt
joke861110.egg-info/not-zip-safe
joke861110.egg-info/top_level.txt