Metadata-Version: 1.0
Name: joke861110
Version: 0.2
Summary: jip joke
Home-page: https://github.com/dev-jip/joke861110.git
Author: jip
Author-email: herejip@gmail.com
License: JIP Entertainment
Platform: UNKNOWN
